LICENSE
MANIFEST.in
README.md
pyproject.toml
setup.cfg
setup.py
docs/README.md
mlhub/__init__.py
mlhub/commands.py
mlhub/constants.py
mlhub/pkg.py
mlhub/utils.py
mlhub.egg-info/PKG-INFO
mlhub.egg-info/SOURCES.txt
mlhub.egg-info/SOURCES.txt.~1~
mlhub.egg-info/dependency_links.txt
mlhub.egg-info/entry_points.txt
mlhub.egg-info/requires.txt
mlhub.egg-info/top_level.txt
mlhub/bash_completion.d/ml.bash
mlhub/scripts/convert_readme.sh
mlhub/scripts/dep/mlhub.sh
mlhub/scripts/dep/python.sh
mlhub/scripts/dep/r.R
mlhub/scripts/dep/system.sh
mlhub/scripts/dep/utils.sh