Metadata-Version: 2.2
Name: mlhub
Version: 3.11.7
Summary: Machine learning model repository manager
Home-page: https://mlhub.ai
Author: Graham Williams
Author-email: mlhub@togaware.com
Keywords: machine learning models repository
Classifier: Development Status :: 5 - Production/Stable
Classifier: Environment :: Console
Classifier: Intended Audience :: End Users/Desktop
Classifier: License :: OSI Approved :: MIT License
Classifier: Programming Language :: Python :: 3
License-File: LICENSE
Requires-Dist: distro
Requires-Dist: gdown
Requires-Dist: rapidfuzz
Requires-Dist: pyyaml
Requires-Dist: requests
Requires-Dist: yamlordereddictloader
Dynamic: author
Dynamic: author-email
Dynamic: classifier
Dynamic: description
Dynamic: description-content-type
Dynamic: home-page
Dynamic: keywords
Dynamic: requires-dist
Dynamic: summary
